dotations_locales_back/__init__.py
dotations_locales_back/common/__init__.py
dotations_locales_back/common/init_datas.py
dotations_locales_back/common/load_dgcl_criteres_data.py
dotations_locales_back/common/load_dgcl_dotations_data.py
dotations_locales_back/common/mapping/criteres_dgcl_2020.py
dotations_locales_back/common/mapping/criteres_dgcl_2021.py
dotations_locales_back/common/mapping/criteres_dgcl_2022.py
dotations_locales_back/common/mapping/criteres_generaux.py
dotations_locales_back/common/mapping/dotation_forfaitaire.py
dotations_locales_back/common/mapping/dotation_nationale_perequation.py
dotations_locales_back/common/mapping/dotation_solidarite_rurale.py
dotations_locales_back/common/mapping/dotation_solidarite_urbaine.py
dotations_locales_back/common/search_commune.py
dotations_locales_back/simulation/__init__.py
dotations_locales_back/simulation/load_dgcl_data.py
dotations_locales_back/simulation/simulation.py
dotations_locales_back/web_api/__init__.py
dotations_locales_back/web_api/main.py
dotations_locales_back/web_api/utils.py
dotations_locales_back-1.3.6.dist-info/LICENSE
dotations_locales_back-1.3.6.dist-info/WHEEL
dotations_locales_back-1.3.6.dist-info/METADATA
dotations_locales_back-1.3.6.dist-info/RECORD
