Metadata-Version: 2.1
Name: dotations-locales-back
Version: 1.3.6
Summary: Le dorsal de dotations.incubateur.anct.gouv.fr
Home-page: https://gitlab.com/incubateur-territoires/startups/dotations-locales/dotations-locales-back/
License: AGPL-3.0-or-later
Author: Equipe Dotations Locales
Author-email: contact-dotations-locales@anct.gouv.fr
Requires-Python: >=3.8,<4.0
Classifier: License :: OSI Approved :: GNU Affero General Public License v3 or later (AGPLv3+)
Classifier: Programming Language :: Python :: 3
Classifier: Programming Language :: Python :: 3.10
Classifier: Programming Language :: Python :: 3.8
Classifier: Programming Language :: Python :: 3.9
Requires-Dist: OpenFisca-France-Dotations-Locales (>=0.8.1,<0.9.0)
Requires-Dist: fastapi (>=0.78.0,<0.79.0)
Requires-Dist: pandas (>=1.3,<2.0)
Requires-Dist: uvicorn (>=0.18.2,<0.19.0)
Project-URL: Repository, https://gitlab.com/incubateur-territoires/startups/dotations-locales/dotations-locales-back/
